lucid/__init__.py
lucid/error.py
lucid/port.py
lucid/types.py
lucid/_backend/__init__.py
lucid/_backend/conv.py
lucid/_backend/core.py
lucid/_backend/metal.py
lucid/_backend/pool.py
lucid/_func/__init__.py
lucid/_func/bfunc.py
lucid/_func/gfunc.py
lucid/_func/ufunc.py
lucid/_fusion/__init__.py
lucid/_fusion/base.py
lucid/_fusion/func.py
lucid/_tensor/__init__.py
lucid/_tensor/tensor.py
lucid/_tensor/tensor_ops.py
lucid/_util/__init__.py
lucid/_util/func.py
lucid/data/__init__.py
lucid/data/_base.py
lucid/data/_util.py
lucid/datasets/__init__.py
lucid/datasets/_base.py
lucid/datasets/cifar.py
lucid/datasets/mnist.py
lucid/einops/__init__.py
lucid/einops/_func.py
lucid/linalg/__init__.py
lucid/linalg/_func.py
lucid/models/__init__.py
lucid/models/util.py
lucid/models/imgclf/__init__.py
lucid/models/imgclf/alex.py
lucid/models/imgclf/coatnet.py
lucid/models/imgclf/convnext.py
lucid/models/imgclf/crossvit.py
lucid/models/imgclf/cspnet.py
lucid/models/imgclf/cvt.py
lucid/models/imgclf/dense.py
lucid/models/imgclf/efficient.py
lucid/models/imgclf/efficientformer.py
lucid/models/imgclf/inception.py
lucid/models/imgclf/inception_next.py
lucid/models/imgclf/inception_res.py
lucid/models/imgclf/lenet.py
lucid/models/imgclf/maxvit.py
lucid/models/imgclf/mobile.py
lucid/models/imgclf/pvt.py
lucid/models/imgclf/resnest.py
lucid/models/imgclf/resnet.py
lucid/models/imgclf/resnext.py
lucid/models/imgclf/senet.py
lucid/models/imgclf/sknet.py
lucid/models/imgclf/swin.py
lucid/models/imgclf/vgg.py
lucid/models/imgclf/vit.py
lucid/models/imgclf/xception.py
lucid/models/imgclf/zfnet.py
lucid/models/imggen/__init__.py
lucid/models/imggen/ddpm.py
lucid/models/imggen/vae.py
lucid/models/objdet/__init__.py
lucid/models/objdet/detr.py
lucid/models/objdet/efficientdet.py
lucid/models/objdet/fast_rcnn.py
lucid/models/objdet/faster_rcnn.py
lucid/models/objdet/rcnn.py
lucid/models/objdet/util.py
lucid/models/objdet/yolo/__init__.py
lucid/models/objdet/yolo/yolo_v1.py
lucid_dl-2.10.0.dist-info/licenses/LICENSE
lucid_dl-2.10.0.dist-info/METADATA
lucid_dl-2.10.0.dist-info/WHEEL
lucid_dl-2.10.0.dist-info/top_level.txt
lucid_dl-2.10.0.dist-info/RECORD
