Metadata-Version: 2.4
Name: lucid-dl
Version: 2.10.0
Summary: Lumerico's Comprehensive Interface for Deep Learning
Home-page: https://github.com/ChanLumerico/lucid
Author: ChanLumerico
Author-email: greensox284@gmail.com
Classifier: Programming Language :: Python :: 3
Classifier: License :: OSI Approved :: MIT License
Classifier: Operating System :: OS Independent
Requires-Python: >=3.12
License-File: LICENSE
Requires-Dist: numpy
Requires-Dist: pandas
Requires-Dist: openml
Requires-Dist: mlx
Dynamic: author
Dynamic: author-email
Dynamic: classifier
Dynamic: description
Dynamic: description-content-type
Dynamic: home-page
Dynamic: license-file
Dynamic: requires-dist
Dynamic: requires-python
Dynamic: summary
